hnoca/__init__.py
hnoca/_logging.py
hnoca/mapping/__init__.py
hnoca/mapping/mapper.py
hnoca/mapping/matching.py
hnoca/mapping/utils.py
hnoca/mapping/wknn.py
hnoca/snapseed/__init__.py
hnoca/snapseed/annotate.py
hnoca/snapseed/auroc.py
hnoca/snapseed/colors.py
hnoca/snapseed/markers.py
hnoca/snapseed/utils.py
hnoca/stats/__init__.py
hnoca/stats/de.py
hnoca/stats/pseudobulk.py
hnoca/stats/tests.py
hnoca/utils/__init__.py
hnoca/utils/check.py
hnoca/utils/stress.py
hnoca-0.2.1.dist-info/METADATA
hnoca-0.2.1.dist-info/WHEEL
hnoca-0.2.1.dist-info/licenses/LICENSE
hnoca-0.2.1.dist-info/RECORD
