Metadata-Version: 2.4
Name: hnoca
Version: 0.2.1
Summary: Human Neural Organoid Cell Atlas Toolbox
Project-URL: Documentation, https://devsystemslab.github.io/HNOCA-tools/
Project-URL: Homepage, https://github.com/devsystemslab/HNOCA-tools
Project-URL: Source, https://github.com/devsystemslab/HNOCA-tools
Author: Jonas Simon Fleck, Zhisong He, Leander Dony
Maintainer-email: Jonas Simon Fleck <jonas_simon.fleck@roche.com>, Zhisong He <zhisong.he@bsse.ethz.ch>, Leander Dony <leander.dony@helmholtz-munich.de>
License:                     GNU GENERAL PUBLIC LICENSE
License-File: LICENSE
Classifier: Programming Language :: Python :: 3 :: Only
Classifier: Programming Language :: Python :: 3.10
Classifier: Programming Language :: Python :: 3.11
Classifier: Programming Language :: Python :: 3.12
Classifier: Programming Language :: Python :: 3.13
Requires-Python: >=3.10
Requires-Dist: anndata>=0.10
Requires-Dist: cloudpickle>=3
Requires-Dist: jax>=0.4
Requires-Dist: jaxlib>=0.4
Requires-Dist: joblib>=1.4
Requires-Dist: matplotlib>=3.10
Requires-Dist: numba>=0.58
Requires-Dist: numpy>=1.26.4
Requires-Dist: pandas>=2
Requires-Dist: scanpy>=1.11
Requires-Dist: scikit-learn>=1.1.3
Requires-Dist: scipy>=1.15
Requires-Dist: session-info2
Requires-Dist: statsmodels>=0.14.2
Provides-Extra: dev
Requires-Dist: pre-commit; extra == 'dev'
Requires-Dist: twine>=4.0.2; extra == 'dev'
Provides-Extra: doc
Requires-Dist: mkdocs-macros-plugin; extra == 'doc'
Requires-Dist: mkdocs-material; extra == 'doc'
Requires-Dist: mkdocstrings[python]; extra == 'doc'
Requires-Dist: mknotebooks; extra == 'doc'
Requires-Dist: pymdown-extensions; extra == 'doc'
Provides-Extra: mapping
Requires-Dist: scarches>=0.6.1; extra == 'mapping'
Requires-Dist: scvi-tools>=1.2; extra == 'mapping'
Provides-Extra: stats
Requires-Dist: decoupler>=1.6; extra == 'stats'
Provides-Extra: test
Requires-Dist: coverage; extra == 'test'
Requires-Dist: igraph>=0.11; extra == 'test'
Requires-Dist: pytest; extra == 'test'
Requires-Dist: pyyaml; extra == 'test'
Requires-Dist: rich; extra == 'test'
